genderdetectfrance.py
genderdetectfrance-1.0.2.dist-info/LICENSE
genderdetectfrance-1.0.2.dist-info/METADATA
genderdetectfrance-1.0.2.dist-info/WHEEL
genderdetectfrance-1.0.2.dist-info/top_level.txt
genderdetectfrance-1.0.2.dist-info/RECORD
