Metadata-Version: 2.1
Name: genderdetectfrance
Version: 1.0.2
Summary: Detect sex from german, french, italian first names
Home-page: UNKNOWN
Author: Marcel Mateescu
License: UNKNOWN
Platform: UNKNOWN
Classifier: Programming Language :: Python :: 3
Classifier: License :: OSI Approved :: MIT License
Classifier: Operating System :: OS Independent
Requires-Python: >=3.6
